Workbook
Name patrimonio: 'Página1'!$E$20
Name taxa_mensal: 'Página1'!$E$19
Name qtd_anos: 'Página1'!$E$18
Name rendimento_carteira: 'Página1'!$E$12
Name aporte: 'Página1'!$E$17
Name sugestao_inestimento: 'Página1'!$E$13

Sheet Página1
B10: Configurações
B11: salário | E11: 4200
B12: rendimento carteira | E12: 0.006
B13: sugesttão de investimento | E13: =E11*30% -> 1260
B16: investimento mensal
B17: Quanto investir por mês; | E17: 1260
B18: Por quantos anos; | E18: 10
B19: Qual a taxa de rendimento mensal; | E19: 0.0108
B20: Quanto de patrimônio vai acumular? | E20: =FV(taxa_mensal,qtd_anos*12,aporte*-1) -> 306756.66
B21: Quanto vai receber de dividendos por mês? | E21: =patrimonio*rendimento_carteira -> 1840.54
B24: Cenários | F24: dividendo
B25: Quantos em 2 anos? | E25: =FV($E$19,12*2,E17*-1) -> 34310.888 | F25: =E25*rendimento_carteira -> 205.86533
B26: Quantos em 5 anos? | E26: =FV($E$19,12*5,E17*-1) -> 105593.06 | F26: =E26*rendimento_carteira -> 633.55839
B27: Quantos em 10 anos? | E27: =FV($E$19,12*10,E17*-1) -> 306756.66 | F27: =E27*rendimento_carteira -> 1840.54
B28: Quantos em 20 anos ? | E28: =FV($E$19,12*20,E17*-1) -> 1420081.7 | F28: =E28*rendimento_carteira -> 8520.4904
B29: Quantos em 30 anos? | E29: =FV($E$19,12*30,E17*-1) -> 5460720.1 | F29: =E29*rendimento_carteira -> 32764.32
B32: Perfil | C32: Moderado
B33: Valor a ser investido por mês | C33: =aporte -> 1260
B36: Tipo de FII | C36: Percentual Sugerido | D36: Valores
B37: Papel | C37: =VLOOKUP($C$32&"-"&B37,'Página2'!$A1:$D19,4,false) -> 0.32 | D37: =C37*$C$33 -> 403.2
B38: Tijolo | C38: =VLOOKUP($C$32&"-"&B38,'Página2'!$A2:$D20,4,false) -> 0.35 | D38: =C38*$C$33 -> 441
B39: Hibridos | C39: =VLOOKUP($C$32&"-"&B39,'Página2'!$A3:$D21,4,false) -> 0.08 | D39: =C39*$C$33 -> 100.8
B40: FOF'S | C40: =VLOOKUP($C$32&"-"&B40,'Página2'!$A4:$D22,4,false) -> 0.05 | D40: =C40*$C$33 -> 63
B41: Desenvolvimento | C41: =VLOOKUP($C$32&"-"&B41,'Página2'!$A5:$D23,4,false) -> 0.1 | D41: =C41*$C$33 -> 126
B42: Hotelarias | C42: =VLOOKUP($C$32&"-"&B42,'Página2'!$A6:$D24,4,false) -> 0.1 | D42: =C42*$C$33 -> 126

Sheet Página2
A1: CHAVE | B1: perfil | C1: tipo de FII | D1: %
A2: =B2&"-"&C2 -> Conservador-Papel | B2: Conservador | C2: Papel | D2: 0.3 | F2: moderado-Tijolo | G2: =VLOOKUP(F2,$A:$D,4,false) -> 0.35
A3: =B3&"-"&C3 -> Conservador-Tijolo | B3: Conservador | C3: Tijolo | D3: 0.5
A4: =B4&"-"&C4 -> Conservador-Hibridos | B4: Conservador | C4: Hibridos | D4: 0.1
A5: =B5&"-"&C5 -> Conservador-FOF'S | B5: Conservador | C5: FOF'S | D5: 0.1
A6: =B6&"-"&C6 -> Conservador-Desenvolvimento | B6: Conservador | C6: Desenvolvimento | D6: 0
A7: =B7&"-"&C7 -> Conservador-Hotelarias | B7: Conservador | C7: Hotelarias | D7: 0
A8: =B8&"-"&C8 -> Moderado-Papel | B8: Moderado | C8: Papel | D8: 0.32
A9: =B9&"-"&C9 -> Moderado-Tijolo | B9: Moderado | C9: Tijolo | D9: 0.35
A10: =B10&"-"&C10 -> Moderado-Hibridos | B10: Moderado | C10: Hibridos | D10: 0.08
A11: =B11&"-"&C11 -> Moderado-FOF'S | B11: Moderado | C11: FOF'S | D11: 0.05
A12: =B12&"-"&C12 -> Moderado-Desenvolvimento | B12: Moderado | C12: Desenvolvimento | D12: 0.1
A13: =B13&"-"&C13 -> Moderado-Hotelarias | B13: Moderado | C13: Hotelarias | D13: 0.1
A14: =B14&"-"&C14 -> agressivo-Papel | B14: agressivo | C14: Papel | D14: 0.5
... A19: =B19&"-"&C19 -> agressivo-Hotelarias | B19: agressivo | C19: Hotelarias | D19: 0.1
